Metadata-Version: 2.2
Name: sagace
Version: 0.1.4
Summary: SAGACE Package - Auxiliary package for developing integrations with the SAGACE system.
Home-page: https://gitlab.com/ampere.consultoria/sagace-python-sdk.git
Author: Ampere Consultoria Empresaria LTDA
Author-email: Ampere Consultoria Empresaria LTDA <desenvolvimento@ampereconsultoria.com.br>
License: MIT
Project-URL: homepage, https://gitlab.com/ampere.consultoria/sagace-python-sdk
Project-URL: repository, https://gitlab.com/ampere.consultoria/sagace-python-sdk
Keywords: sagace,energy,integrations,ampere
Classifier: Programming Language :: Python :: 3
Classifier: License :: OSI Approved :: MIT License
Classifier: Operating System :: OS Independent
Classifier: Development Status :: 3 - Alpha
Classifier: Intended Audience :: Developers
Classifier: Topic :: Software Development :: Libraries
Requires-Python: >=3.7
License-File: LICENSE
Dynamic: author
Dynamic: home-page
Dynamic: requires-python
